{"searchResultMetaData":{"branded":true,"multipleDateResult":true,"composedResult":false,"interlineRoute":false,"contextShopping":false},"fareFamilies":[{"brandId":"YF","brandLabel":[{"programId":"124499","languageId":"en_GB","marketingText":"Economy Choice Plus"},{"programId":"124499","languageId":"ar_AE","marketingText":"Economy Choice Plus"},{"programId":"124499","languageId":"zh_CN","marketingText":"Economy Choice Plus"},{"programId":"124499","languageId":"nl_NL","marketingText":"Economy Choice Plus"},{"programId":"124499","languageId":"fr_FR","marketingText":"Economy Choice Plus"},{"programId":"124499","languageId":"de_DE","marketingText":"Economy Choice Plus"},{"programId":"124499","languageId":"el_GR","marketingText":"Economy Choice Plus"},{"programId":"124499","languageId":"it_IT","marketingText":"Economy Choice Plus"},{"programId":"124499","languageId":"ja_JP","marketingText":"Economy Choice Plus"},{"programId":"124499","languageId":"ko_KR","marketingText":"Economy Choice Plus"},{"programId":"124499","languageId":"pt_BR","marketingText":"Economy Choice Plus"},{"programId":"124499","languageId":"ru_RU","marketingText":"Economy Choice Plus"},{"programId":"124499","languageId":"es_ES","marketingText":"Economy Choice Plus"},{"programId":"124499","languageId":"th_TH","marketingText":"Economy Choice Plus"},{"programId":"124499","languageId":"tr_TR","marketingText":"Economy Choice Plus"}],"marketingTexts":[{"programId":"124499","languageId":"en_GB"},{"programId":"124499","languageId":"ar_AE"},{"programId":"124499","languageId":"zh_CN"},{"programId":"124499","languageId":"nl_NL"},{"programId":"124499","languageId":"fr_FR"},{"programId":"124499","languageId":"de_DE"},{"programId":"124499","languageId":"el_GR"},{"programId":"124499","languageId":"it_IT"},{"programId":"124499","languageId":"ja_JP"},{"programId":"124499","languageId":"ko_KR"},{"programId":"124499","languageId":"pt_BR"},{"programId":"124499","languageId":"ru_RU"},{"programId":"124499","languageId":"es_ES"},{"programId":"124499","languageId":"th_TH"},{"programId":"124499","languageId":"tr_TR"}],"brandAncillaries":{"flightAncillary":[]},"fareFamilyRemarkRPH":0},{"brandId":"YS","brandLabel":[{"programId":"124499","languageId":"en_GB","marketingText":"Economy Sale"},{"programId":"124499","languageId":"ar_AE","marketingText":"Economy Sale"},{"programId":"124499","languageId":"zh_CN","marketingText":"Economy Sale"},{"programId":"124499","languageId":"nl_NL","marketingText":"Economy Sale"},{"programId":"124499","languageId":"fr_FR","marketingText":"Economy Sale"},{"programId":"124499","languageId":"de_DE","marketingText":"Economy Sale"},{"programId":"124499","languageId":"el_GR","marketingText":"Economy Sale"},{"programId":"124499","languageId":"it_IT","marketingText":"Economy Sale"},{"programId":"124499","languageId":"ja_JP","marketingText":"Economy Sale"},{"programId":"124499","languageId":"ko_KR","marketingText":"Economy Sale"},{"programId":"124499","languageId":"pt_BR","marketingText":"Economy Sale"},{"programId":"124499","languageId":"ru_RU","marketingText":"Economy Sale"},{"programId":"124499","languageId":"es_ES","marketingText":"Economy Sale"},{"programId":"124499","languageId":"th_TH","marketingText":"Economy Sale"},{"programId":"124499","languageId":"tr_TR","marketingText":"Economy Sale"}],"marketingTexts":[{"programId":"124499","languageId":"en_GB"},{"programId":"124499","languageId":"ar_AE"},{"programId":"124499","languageId":"zh_CN"},{"programId":"124499","languageId":"nl_NL"},{"programId":"124499","languageId":"fr_FR"},{"programId":"124499","languageId":"de_DE"},{"programId":"124499","languageId":"el_GR"},{"programId":"124499","languageId":"it_IT"},{"programId":"124499","languageId":"ja_JP"},{"programId":"124499","languageId":"ko_KR"},{"programId":"124499","languageId":"pt_BR"},{"programId":"124499","languageId":"ru_RU"},{"programId":"124499","languageId":"es_ES"},{"programId":"124499","languageId":"th_TH"},{"programId":"124499","languageId":"tr_TR"}],"brandAncillaries":{"flightAncillary":[]},"fareFamilyRemarkRPH":0},{"brandId":"YH","brandLabel":[{"programId":"124499","languageId":"en_GB","marketingText":"Economy Hand Baggage Only"},{"programId":"124499","languageId":"ar_AE","marketingText":"Economy Hand Baggage Only"},{"programId":"124499","languageId":"zh_CN","marketingText":"Economy Hand Baggage Only"},{"programId":"124499","languageId":"nl_NL","marketingText":"Economy Hand Baggage Only"},{"programId":"124499","languageId":"fr_FR","marketingText":"Economy Hand Baggage Only"},{"programId":"124499","languageId":"de_DE","marketingText":"Economy Hand Baggage Only"},{"programId":"124499","languageId":"el_GR","marketingText":"Economy Hand Baggage Only"},{"programId":"124499","languageId":"it_IT","marketingText":"Economy Hand Baggage Only"},{"programId":"124499","languageId":"ja_JP","marketingText":"Economy Hand Baggage Only"},{"programId":"124499","languageId":"ko_KR","marketingText":"Economy Hand Baggage Only"},{"programId":"124499","languageId":"pt_BR","marketingText":"Economy Hand Baggage Only"},{"programId":"124499","languageId":"ru_RU","marketingText":"Economy Hand Baggage Only"},{"programId":"124499","languageId":"es_ES","marketingText":"Economy Hand Baggage Only"},{"programId":"124499","languageId":"th_TH","marketingText":"Economy Hand Baggage Only"},{"programId":"124499","languageId":"tr_TR","marketingText":"Economy Hand Baggage Only"}],"marketingTexts":[{"programId":"124499","languageId":"en_GB"},{"programId":"124499","languageId":"ar_AE"},{"programId":"124499","languageId":"zh_CN"},{"programId":"124499","languageId":"nl_NL"},{"programId":"124499","languageId":"fr_FR"},{"programId":"124499","languageId":"de_DE"},{"programId":"124499","languageId":"el_GR"},{"programId":"124499","languageId":"it_IT"},{"programId":"124499","languageId":"ja_JP"},{"programId":"124499","languageId":"ko_KR"},{"programId":"124499","languageId":"pt_BR"},{"programId":"124499","languageId":"ru_RU"},{"programId":"124499","languageId":"es_ES"},{"programId":"124499","languageId":"th_TH"},{"programId":"124499","languageId":"tr_TR"}],"brandAncillaries":{"flightAncillary":[]},"fareFamilyRemarkRPH":0},{"brandId":"YV","brandLabel":[{"programId":"124499","languageId":"en_GB","marketingText":"Economy Value"},{"programId":"124499","languageId":"ar_AE","marketingText":"Economy Value"},{"programId":"124499","languageId":"zh_CN","marketingText":"Economy Value"},{"programId":"124499","languageId":"nl_NL","marketingText":"Economy Value"},{"programId":"124499","languageId":"fr_FR","marketingText":"Economy Value"},{"programId":"124499","languageId":"de_DE","marketingText":"Economy Value"},{"programId":"124499","languageId":"el_GR","marketingText":"Economy Value"},{"programId":"124499","languageId":"it_IT","marketingText":"Economy Value"},{"programId":"124499","languageId":"ja_JP","marketingText":"Economy Value"},{"programId":"124499","languageId":"ko_KR","marketingText":"Economy Value"},{"programId":"124499","languageId":"pt_BR","marketingText":"Economy Value"},{"programId":"124499","languageId":"ru_RU","marketingText":"Economy Value"},{"programId":"124499","languageId":"es_ES","marketingText":"Economy Value"},{"programId":"124499","languageId":"th_TH","marketingText":"Economy Value"},{"programId":"124499","languageId":"tr_TR","marketingText":"Economy Value"}],"marketingTexts":[{"programId":"124499","languageId":"en_GB"},{"programId":"124499","languageId":"ar_AE"},{"programId":"124499","languageId":"zh_CN"},{"programId":"124499","languageId":"nl_NL"},{"programId":"124499","languageId":"fr_FR"},{"programId":"124499","languageId":"de_DE"},{"programId":"124499","languageId":"el_GR"},{"programId":"124499","languageId":"it_IT"},{"programId":"124499","languageId":"ja_JP"},{"programId":"124499","languageId":"ko_KR"},{"programId":"124499","languageId":"pt_BR"},{"programId":"124499","languageId":"ru_RU"},{"programId":"124499","languageId":"es_ES"},{"programId":"124499","languageId":"th_TH"},{"programId":"124499","languageId":"tr_TR"}],"brandAncillaries":{"flightAncillary":[]},"fareFamilyRemarkRPH":0},{"brandId":"YC","brandLabel":[{"programId":"124499","languageId":"en_GB","marketingText":"Economy Choice"},{"programId":"124499","languageId":"ar_AE","marketingText":"Economy Choice"},{"programId":"124499","languageId":"zh_CN","marketingText":"Economy Choice"},{"programId":"124499","languageId":"nl_NL","marketingText":"Economy Choice"},{"programId":"124499","languageId":"fr_FR","marketingText":"Economy Choice"},{"programId":"124499","languageId":"de_DE","marketingText":"Economy Choice"},{"programId":"124499","languageId":"el_GR","marketingText":"Economy Choice"},{"programId":"124499","languageId":"it_IT","marketingText":"Economy Choice"},{"programId":"124499","languageId":"ja_JP","marketingText":"Economy Choice"},{"programId":"124499","languageId":"ko_KR","marketingText":"Economy Choice"},{"programId":"124499","languageId":"pt_BR","marketingText":"Economy Choice"},{"programId":"124499","languageId":"ru_RU","marketingText":"Economy Choice"},{"programId":"124499","languageId":"es_ES","marketingText":"Economy Choice"},{"programId":"124499","languageId":"th_TH","marketingText":"Economy Choice"},{"programId":"124499","languageId":"tr_TR","marketingText":"Economy Choice"}],"marketingTexts":[{"programId":"124499","languageId":"en_GB"},{"programId":"124499","languageId":"ar_AE"},{"programId":"124499","languageId":"zh_CN"},{"programId":"124499","languageId":"nl_NL"},{"programId":"124499","languageId":"fr_FR"},{"programId":"124499","languageId":"de_DE"},{"programId":"124499","languageId":"el_GR"},{"programId":"124499","languageId":"it_IT"},{"programId":"124499","languageId":"ja_JP"},{"programId":"124499","languageId":"ko_KR"},{"programId":"124499","languageId":"pt_BR"},{"programId":"124499","languageId":"ru_RU"},{"programId":"124499","languageId":"es_ES"},{"programId":"124499","languageId":"th_TH"},{"programId":"124499","languageId":"tr_TR"}],"brandAncillaries":{"flightAncillary":[]},"fareFamilyRemarkRPH":0},{"brandId":"JV","brandLabel":[{"programId":"124499","languageId":"en_GB","marketingText":"Business Value"},{"programId":"124499","languageId":"ar_AE","marketingText":"Business Value"},{"programId":"124499","languageId":"zh_CN","marketingText":"Business Value"},{"programId":"124499","languageId":"nl_NL","marketingText":"Business Value"},{"programId":"124499","languageId":"fr_FR","marketingText":"Business Value"},{"programId":"124499","languageId":"de_DE","marketingText":"Business Value"},{"programId":"124499","languageId":"el_GR","marketingText":"Business Value"},{"programId":"124499","languageId":"it_IT","marketingText":"Business Value"},{"programId":"124499","languageId":"ja_JP","marketingText":"Business Value"},{"programId":"124499","languageId":"ko_KR","marketingText":"Business Value"},{"programId":"124499","languageId":"pt_BR","marketingText":"Business Value"},{"programId":"124499","languageId":"ru_RU","marketingText":"Business Value"},{"programId":"124499","languageId":"es_ES","marketingText":"Business Value"},{"programId":"124499","languageId":"th_TH","marketingText":"Business Value"},{"programId":"124499","languageId":"tr_TR","marketingText":"Business Value"}],"marketingTexts":[{"programId":"124499","languageId":"en_GB"},{"programId":"124499","languageId":"ar_AE"},{"programId":"124499","languageId":"zh_CN"},{"programId":"124499","languageId":"nl_NL"},{"programId":"124499","languageId":"fr_FR"},{"programId":"124499","languageId":"de_DE"},{"programId":"124499","languageId":"el_GR"},{"programId":"124499","languageId":"it_IT"},{"programId":"124499","languageId":"ja_JP"},{"programId":"124499","languageId":"ko_KR"},{"programId":"124499","languageId":"pt_BR"},{"programId":"124499","languageId":"ru_RU"},{"programId":"124499","languageId":"es_ES"},{"programId":"124499","languageId":"th_TH"},{"programId":"124499","languageId":"tr_TR"}],"brandAncillaries":{"flightAncillary":[]},"fareFamilyRemarkRPH":0},{"brandId":"JC","brandLabel":[{"programId":"124499","languageId":"en_GB","marketingText":"Business Choice"},{"programId":"124499","languageId":"ar_AE","marketingText":"Business Choice"},{"programId":"124499","languageId":"zh_CN","marketingText":"Business Choice"},{"programId":"124499","languageId":"nl_NL","marketingText":"Business Choice"},{"programId":"124499","languageId":"fr_FR","marketingText":"Business Choice"},{"programId":"124499","languageId":"de_DE","marketingText":"Business Choice"},{"programId":"124499","languageId":"el_GR","marketingText":"Business Choice"},{"programId":"124499","languageId":"it_IT","marketingText":"Business Choice"},{"programId":"124499","languageId":"ja_JP","marketingText":"Business Choice"},{"programId":"124499","languageId":"ko_KR","marketingText":"Business Choice"},{"programId":"124499","languageId":"pt_BR","marketingText":"Business Choice"},{"programId":"124499","languageId":"ru_RU","marketingText":"Business Choice"},{"programId":"124499","languageId":"es_ES","marketingText":"Business Choice"},{"programId":"124499","languageId":"th_TH","marketingText":"Business Choice"},{"programId":"124499","languageId":"tr_TR","marketingText":"Business Choice"}],"marketingTexts":[{"programId":"124499","languageId":"en_GB"},{"programId":"124499","languageId":"ar_AE"},{"programId":"124499","languageId":"zh_CN"},{"programId":"124499","languageId":"nl_NL"},{"programId":"124499","languageId":"fr_FR"},{"programId":"124499","languageId":"de_DE"},{"programId":"124499","languageId":"el_GR"},{"programId":"124499","languageId":"it_IT"},{"programId":"124499","languageId":"ja_JP"},{"programId":"124499","languageId":"ko_KR"},{"programId":"124499","languageId":"pt_BR"},{"programId":"124499","languageId":"ru_RU"},{"programId":"124499","languageId":"es_ES"},{"programId":"124499","languageId":"th_TH"},{"programId":"124499","languageId":"tr_TR"}],"brandAncillaries":{"flightAncillary":[]},"fareFamilyRemarkRPH":0},{"brandId":"JF","brandLabel":[{"programId":"124499","languageId":"en_GB","marketingText":"Business Choice Plus"},{"programId":"124499","languageId":"ar_AE","marketingText":"Business Choice Plus"},{"programId":"124499","languageId":"zh_CN","marketingText":"Business Choice Plus"},{"programId":"124499","languageId":"nl_NL","marketingText":"Business Choice Plus"},{"programId":"124499","languageId":"fr_FR","marketingText":"Business Choice Plus"},{"programId":"124499","languageId":"de_DE","marketingText":"Business Choice Plus"},{"programId":"124499","languageId":"el_GR","marketingText":"Business Choice Plus"},{"programId":"124499","languageId":"it_IT","marketingText":"Business Choice Plus"},{"programId":"124499","languageId":"ja_JP","marketingText":"Business Choice Plus"},{"programId":"124499","languageId":"ko_KR","marketingText":"Business Choice Plus"},{"programId":"124499","languageId":"pt_BR","marketingText":"Business Choice Plus"},{"programId":"124499","languageId":"ru_RU","marketingText":"Business Choice Plus"},{"programId":"124499","languageId":"es_ES","marketingText":"Business Choice Plus"},{"programId":"124499","languageId":"th_TH","marketingText":"Business Choice Plus"},{"programId":"124499","languageId":"tr_TR","marketingText":"Business Choice Plus"}],"marketingTexts":[{"programId":"124499","languageId":"en_GB"},{"programId":"124499","languageId":"ar_AE"},{"programId":"124499","languageId":"zh_CN"},{"programId":"124499","languageId":"nl_NL"},{"programId":"124499","languageId":"fr_FR"},{"programId":"124499","languageId":"de_DE"},{"programId":"124499","languageId":"el_GR"},{"programId":"124499","languageId":"it_IT"},{"programId":"124499","languageId":"ja_JP"},{"programId":"124499","languageId":"ko_KR"},{"programId":"124499","languageId":"pt_BR"},{"programId":"124499","languageId":"ru_RU"},{"programId":"124499","languageId":"es_ES"},{"programId":"124499","languageId":"th_TH"},{"programId":"124499","languageId":"tr_TR"}],"brandAncillaries":{"flightAncillary":[]},"fareFamilyRemarkRPH":0}],"unbundledOffers":[[{"shoppingBasketHashCode":-737958418,"brandId":"YF","soldout":false,"bundlePrice":{},"availableObFees":[],"seatsRemaining":{"count":9,"lowAvailability":false},"itineraryPart":[{"@type":"ItineraryPart","@id":"1","segments":[{"@type":"Segment","@id":"2","segmentOfferInformation":{"flightsMiles":1296,"awardFare":false},"duration":200,"cabinClass":"Economy","equipment":"321","flight":{"flightNumber":599,"operatingFlightNumber":599,"airlineCode":"EY","operatingAirlineCode":"EY","stopAirports":[],"advisories":[],"departureTerminal":"3","arrivalTerminal":"3"},"origin":"TLV","destination":"AUH","departure":"2022-08-19T14:30:00","arrival":"2022-08-19T18:50:00","bookingClass":"Y","layoverDuration":0,"fareBasis":"YF1OW","subjectToGovernmentApproval":false,"fareComponentBeginAirport":"TLV","fareComponentEndAirport":"AUH","fareComponentDirectionality":"FROM","meals":[{"passengerType":"ADT","mealCode":"M"}]},{"@type":"Segment","@id":"3","segmentOfferInformation":{"flightsMiles":2339,"awardFare":false},"duration":350,"cabinClass":"Economy","equipment":"781","flight":{"flightNumber":65,"operatingFlightNumber":65,"airlineCode":"EY","operatingAirlineCode":"EY","stopAirports":[],"advisories":[],"departureTerminal":"3","arrivalTerminal":"C"},"origin":"AUH","destination":"SVO","departure":"2022-08-20T03:35:00","arrival":"2022-08-20T08:25:00","bookingClass":"Y","layoverDuration":0,"fareBasis":"YF1OW","subjectToGovernmentApproval":false,"fareComponentBeginAirport":"AUH","fareComponentEndAirport":"SVO","fareComponentDirectionality":"FROM","meals":[{"passengerType":"ADT","mealCode":"M"}]}],"stops":1,"totalDuration":1075,"connectionInformations":[{"@id":"4","duration":525,"changeOfAirport":false}],"bookingClass":"Y","programIDs":["124499"],"programCodes":["EYA"],"advisories":[]}],"cabinClass":"Economy","offerInformation":{"discounted":false,"negotiated":false,"negotiatedType":"NONE"},"advisories":[],"total":{"alternatives":[[{"amount":2364.61,"currency":"USD"}]]},"fare":{"alternatives":[[{"amount":2192.00,"currency":"USD"}]]},"taxes":{"alternatives":[[{"amount":172.61,"currency":"USD"}]]}},{"shoppingBasketHashCode":1522231966,"brandId":"JF","soldout":false,"bundlePrice":{},"availableObFees":[],"seatsRemaining":{"count":3,"lowAvailability":false},"itineraryPart":[{"@type":"ItineraryPart","@id":"5","segments":[{"@type":"Segment","@id":"6","segmentOfferInformation":{"flightsMiles":1296,"awardFare":false},"duration":200,"cabinClass":"Business","equipment":"321","flight":{"flightNumber":599,"operatingFlightNumber":599,"airlineCode":"EY","operatingAirlineCode":"EY","stopAirports":[],"advisories":[],"departureTerminal":"3","arrivalTerminal":"3"},"origin":"TLV","destination":"AUH","departure":"2022-08-19T14:30:00","arrival":"2022-08-19T18:50:00","bookingClass":"J","layoverDuration":0,"fareBasis":"JF3OW","subjectToGovernmentApproval":false,"fareComponentBeginAirport":"TLV","fareComponentEndAirport":"AUH","fareComponentDirectionality":"FROM","meals":[{"passengerType":"ADT","mealCode":"M"}]},{"@type":"Segment","@id":"7","segmentOfferInformation":{"flightsMiles":2339,"awardFare":false},"duration":350,"cabinClass":"Business","equipment":"781","flight":{"flightNumber":65,"operatingFlightNumber":65,"airlineCode":"EY","operatingAirlineCode":"EY","stopAirports":[],"advisories":[],"departureTerminal":"3","arrivalTerminal":"C"},"origin":"AUH","destination":"SVO","departure":"2022-08-20T03:35:00","arrival":"2022-08-20T08:25:00","bookingClass":"J","layoverDuration":0,"fareBasis":"JF3OW","subjectToGovernmentApproval":false,"fareComponentBeginAirport":"AUH","fareComponentEndAirport":"SVO","fareComponentDirectionality":"FROM","meals":[{"passengerType":"ADT","mealCode":"M"}]}],"stops":1,"totalDuration":1075,"connectionInformations":[{"@id":"8","duration":525,"changeOfAirport":false}],"bookingClass":"J","programIDs":["124499"],"programCodes":["EYA"],"advisories":[]}],"cabinClass":"Business","offerInformation":{"discounted":false,"negotiated":false,"negotiatedType":"NONE"},"advisories":[],"total":{"alternatives":[[{"amount":9670.61,"currency":"USD"}]]},"fare":{"alternatives":[[{"amount":9258.00,"currency":"USD"}]]},"taxes":{"alternatives":[[{"amount":412.61,"currency":"USD"}]]}},{"shoppingBasketHashCode":1186964908,"brandId":"YF","soldout":false,"bundlePrice":{},"availableObFees":[],"seatsRemaining":{"count":4,"lowAvailability":false},"itineraryPart":[{"@type":"ItineraryPart","@id":"9","segments":[{"@type":"Segment","@id":"10","segmentOfferInformation":{"flightsMiles":243,"awardFare":false},"duration":85,"cabinClass":"Economy","equipment":"223","flight":{"flightNumber":592,"operatingFlightNumber":592,"airlineCode":"MS","operatingAirlineCode":"MS","stopAirports":[],"advisories":[],"departureTerminal":"0","arrivalTerminal":"3"},"origin":"TLV","destination":"CAI","departure":"2022-08-19T12:15:00","arrival":"2022-08-19T12:40:00","bookingClass":"K","layoverDuration":0,"fareBasis":"YF1OW","subjectToGovernmentApproval":false,"fareComponentBeginAirport":"TLV","fareComponentEndAirport":"AUH","fareComponentDirectionality":"FROM","meals":[{"passengerType":"ADT","mealCode":"M"}]},{"@type":"Segment","@id":"11","segmentOfferInformation":{"flightsMiles":1464,"awardFare":false},"duration":200,"cabinClass":"Economy","equipment":"321","flight":{"flightNumber":656,"operatingFlightNumber":656,"airlineCode":"EY","operatingAirlineCode":"EY","stopAirports":[],"advisories":[],"departureTerminal":"2","arrivalTerminal":"1"},"origin":"CAI","destination":"AUH","departure":"2022-08-19T17:45:00","arrival":"2022-08-19T23:05:00","bookingClass":"Y","layoverDuration":0,"fareBasis":"YF1OW","subjectToGovernmentApproval":false,"meals":[{"passengerType":"ADT","mealCode":"M"}]},{"@ref":"3"}],"stops":2,"totalDuration":1210,"connectionInformations":[{"@id":"12","duration":305,"changeOfAirport":false},{"@id":"13","duration":270,"changeOfAirport":false}],"bookingClass":"ASSORTED","programIDs":["124499"],"programCodes":["EYA"],"advisories":[]}],"cabinClass":"Economy","offerInformation":{"discounted":false,"negotiated":false,"negotiatedType":"NONE"},"advisories":[],"total":{"alternatives":[[{"amount":2553.29,"currency":"USD"}]]},"fare":{"alternatives":[[{"amount":2284.00,"currency":"USD"}]]},"taxes":{"alternatives":[[{"amount":269.29,"currency":"USD"}]]}}]],"unbundledAlternateDateOffers":[[{"brandId":"YF","soldout":false,"bundlePrice":{},"availableObFees":[],"seatsRemaining":{"count":9,"lowAvailability":false},"itineraryPart":[{"@type":"ItineraryPart","@id":"14","segments":[{"@type":"Segment","@id":"15","segmentOfferInformation":{"flightsMiles":1296,"awardFare":false},"duration":200,"cabinClass":"Economy","equipment":"789","flight":{"flightNumber":599,"operatingFlightNumber":599,"airlineCode":"EY","operatingAirlineCode":"EY","stopAirports":[],"departureTerminal":"3","arrivalTerminal":"3"},"origin":"TLV","destination":"AUH","departure":"2022-08-16T14:30:00","arrival":"2022-08-16T18:50:00","bookingClass":"Y","layoverDuration":0,"fareBasis":"YF1OW","subjectToGovernmentApproval":false,"fareComponentBeginAirport":"TLV","fareComponentEndAirport":"AUH","fareComponentDirectionality":"FROM","meals":[{"passengerType":"ADT","mealCode":"M"}]},{"@type":"Segment","@id":"16","segmentOfferInformation":{"flightsMiles":2339,"awardFare":false},"duration":350,"cabinClass":"Economy","equipment":"781","flight":{"flightNumber":65,"operatingFlightNumber":65,"airlineCode":"EY","operatingAirlineCode":"EY","stopAirports":[],"departureTerminal":"3","arrivalTerminal":"C"},"origin":"AUH","destination":"SVO","departure":"2022-08-17T03:35:00","arrival":"2022-08-17T08:25:00","bookingClass":"Y","layoverDuration":0,"fareBasis":"YF1OW","subjectToGovernmentApproval":false,"fareComponentBeginAirport":"AUH","fareComponentEndAirport":"SVO","fareComponentDirectionality":"FROM","meals":[{"passengerType":"ADT","mealCode":"M"}]}],"stops":1,"totalDuration":1075,"connectionInformations":[{"@id":"17","duration":525,"changeOfAirport":false}],"bookingClass":"Y","programIDs":["124499"],"programCodes":["EYA"]}],"cabinClass":"Economy","offerInformation":{"discounted":false,"negotiated":false,"negotiatedType":"NONE"},"status":"AVAILABLE","departureDates":["2022-08-16"],"total":{"alternatives":[[{"amount":2364.61,"currency":"USD"}]]},"fare":{"alternatives":[[{"amount":2192.00,"currency":"USD"}]]},"taxes":{"alternatives":[[{"amount":172.61,"currency":"USD"}]]}},{"brandId":"YF","soldout":false,"bundlePrice":{},"availableObFees":[],"seatsRemaining":{"count":9,"lowAvailability":false},"itineraryPart":[{"@type":"ItineraryPart","@id":"18","segments":[{"@type":"Segment","@id":"19","segmentOfferInformation":{"flightsMiles":1296,"awardFare":false},"duration":200,"cabinClass":"Economy","equipment":"321","flight":{"flightNumber":599,"operatingFlightNumber":599,"airlineCode":"EY","operatingAirlineCode":"EY","stopAirports":[],"departureTerminal":"3","arrivalTerminal":"3"},"origin":"TLV","destination":"AUH","departure":"2022-08-17T14:55:00","arrival":"2022-08-17T19:15:00","bookingClass":"Y","layoverDuration":0,"fareBasis":"YF1OW","subjectToGovernmentApproval":false,"fareComponentBeginAirport":"TLV","fareComponentEndAirport":"AUH","fareComponentDirectionality":"FROM","meals":[{"passengerType":"ADT","mealCode":"M"}]},{"@type":"Segment","@id":"20","segmentOfferInformation":{"flightsMiles":2339,"awardFare":false},"duration":350,"cabinClass":"Economy","equipment":"781","flight":{"flightNumber":65,"operatingFlightNumber":65,"airlineCode":"EY","operatingAirlineCode":"EY","stopAirports":[],"departureTerminal":"3","arrivalTerminal":"C"},"origin":"AUH","destination":"SVO","departure":"2022-08-18T03:35:00","arrival":"2022-08-18T08:25:00","bookingClass":"Y","layoverDuration":0,"fareBasis":"YF1OW","subjectToGovernmentApproval":false,"fareComponentBeginAirport":"AUH","fareComponentEndAirport":"SVO","fareComponentDirectionality":"FROM","meals":[{"passengerType":"ADT","mealCode":"M"}]}],"stops":1,"totalDuration":1050,"connectionInformations":[{"@id":"21","duration":500,"changeOfAirport":false}],"bookingClass":"Y","programIDs":["124499"],"programCodes":["EYA"]}],"cabinClass":"Economy","offerInformation":{"discounted":false,"negotiated":false,"negotiatedType":"NONE"},"status":"AVAILABLE","departureDates":["2022-08-17"],"total":{"alternatives":[[{"amount":2364.61,"currency":"USD"}]]},"fare":{"alternatives":[[{"amount":2192.00,"currency":"USD"}]]},"taxes":{"alternatives":[[{"amount":172.61,"currency":"USD"}]]}},{"brandId":"YF","soldout":false,"bundlePrice":{},"availableObFees":[],"seatsRemaining":{"count":9,"lowAvailability":false},"itineraryPart":[{"@type":"ItineraryPart","@id":"22","segments":[{"@type":"Segment","@id":"23","segmentOfferInformation":{"flightsMiles":1296,"awardFare":false},"duration":200,"cabinClass":"Economy","equipment":"321","flight":{"flightNumber":599,"operatingFlightNumber":599,"airlineCode":"EY","operatingAirlineCode":"EY","stopAirports":[],"departureTerminal":"3","arrivalTerminal":"3"},"origin":"TLV","destination":"AUH","departure":"2022-08-18T13:30:00","arrival":"2022-08-18T17:50:00","bookingClass":"Y","layoverDuration":0,"fareBasis":"YF1OW","subjectToGovernmentApproval":false,"fareComponentBeginAirport":"TLV","fareComponentEndAirport":"AUH","fareComponentDirectionality":"FROM","meals":[{"passengerType":"ADT","mealCode":"M"}]},{"@type":"Segment","@id":"24","segmentOfferInformation":{"flightsMiles":2339,"awardFare":false},"duration":350,"cabinClass":"Economy","equipment":"781","flight":{"flightNumber":65,"operatingFlightNumber":65,"airlineCode":"EY","operatingAirlineCode":"EY","stopAirports":[],"departureTerminal":"3","arrivalTerminal":"C"},"origin":"AUH","destination":"SVO","departure":"2022-08-19T03:35:00","arrival":"2022-08-19T08:25:00","bookingClass":"Y","layoverDuration":0,"fareBasis":"YF1OW","subjectToGovernmentApproval":false,"fareComponentBeginAirport":"AUH","fareComponentEndAirport":"SVO","fareComponentDirectionality":"FROM","meals":[{"passengerType":"ADT","mealCode":"M"}]}],"stops":1,"totalDuration":1135,"connectionInformations":[{"@id":"25","duration":585,"changeOfAirport":false}],"bookingClass":"Y","programIDs":["124499"],"programCodes":["EYA"]}],"cabinClass":"Economy","offerInformation":{"discounted":false,"negotiated":false,"negotiatedType":"NONE"},"status":"AVAILABLE","departureDates":["2022-08-18"],"total":{"alternatives":[[{"amount":2364.61,"currency":"USD"}]]},"fare":{"alternatives":[[{"amount":2192.00,"currency":"USD"}]]},"taxes":{"alternatives":[[{"amount":172.61,"currency":"USD"}]]}},{"brandId":"YF","soldout":false,"bundlePrice":{},"availableObFees":[],"seatsRemaining":{"count":9,"lowAvailability":false},"itineraryPart":[{"@type":"ItineraryPart","@id":"26","segments":[{"@type":"Segment","@id":"27","segmentOfferInformation":{"flightsMiles":1296,"awardFare":false},"duration":200,"cabinClass":"Economy","equipment":"321","flight":{"flightNumber":599,"operatingFlightNumber":599,"airlineCode":"EY","operatingAirlineCode":"EY","stopAirports":[],"departureTerminal":"3","arrivalTerminal":"3"},"origin":"TLV","destination":"AUH","departure":"2022-08-19T14:30:00","arrival":"2022-08-19T18:50:00","bookingClass":"Y","layoverDuration":0,"fareBasis":"YF1OW","subjectToGovernmentApproval":false,"fareComponentBeginAirport":"TLV","fareComponentEndAirport":"AUH","fareComponentDirectionality":"FROM","meals":[{"passengerType":"ADT","mealCode":"M"}]},{"@type":"Segment","@id":"28","segmentOfferInformation":{"flightsMiles":2339,"awardFare":false},"duration":350,"cabinClass":"Economy","equipment":"781","flight":{"flightNumber":65,"operatingFlightNumber":65,"airlineCode":"EY","operatingAirlineCode":"EY","stopAirports":[],"departureTerminal":"3","arrivalTerminal":"C"},"origin":"AUH","destination":"SVO","departure":"2022-08-20T03:35:00","arrival":"2022-08-20T08:25:00","bookingClass":"Y","layoverDuration":0,"fareBasis":"YF1OW","subjectToGovernmentApproval":false,"fareComponentBeginAirport":"AUH","fareComponentEndAirport":"SVO","fareComponentDirectionality":"FROM","meals":[{"passengerType":"ADT","mealCode":"M"}]}],"stops":1,"totalDuration":1075,"connectionInformations":[{"@id":"29","duration":525,"changeOfAirport":false}],"bookingClass":"Y","programIDs":["124499"],"programCodes":["EYA"]}],"cabinClass":"Economy","offerInformation":{"discounted":false,"negotiated":false,"negotiatedType":"NONE"},"status":"AVAILABLE","departureDates":["2022-08-19"],"total":{"alternatives":[[{"amount":2364.61,"currency":"USD"}]]},"fare":{"alternatives":[[{"amount":2192.00,"currency":"USD"}]]},"taxes":{"alternatives":[[{"amount":172.61,"currency":"USD"}]]}},{"brandId":"YF","soldout":false,"bundlePrice":{},"availableObFees":[],"seatsRemaining":{"count":9,"lowAvailability":false},"itineraryPart":[{"@type":"ItineraryPart","@id":"30","segments":[{"@type":"Segment","@id":"31","segmentOfferInformation":{"flightsMiles":1296,"awardFare":false},"duration":200,"cabinClass":"Economy","equipment":"321","flight":{"flightNumber":599,"operatingFlightNumber":599,"airlineCode":"EY","operatingAirlineCode":"EY","stopAirports":[],"departureTerminal":"3","arrivalTerminal":"3"},"origin":"TLV","destination":"AUH","departure":"2022-08-20T14:30:00","arrival":"2022-08-20T18:50:00","bookingClass":"Y","layoverDuration":0,"fareBasis":"YF1OW","subjectToGovernmentApproval":false,"fareComponentBeginAirport":"TLV","fareComponentEndAirport":"AUH","fareComponentDirectionality":"FROM","meals":[{"passengerType":"ADT","mealCode":"M"}]},{"@type":"Segment","@id":"32","segmentOfferInformation":{"flightsMiles":2339,"awardFare":false},"duration":350,"cabinClass":"Economy","equipment":"781","flight":{"flightNumber":65,"operatingFlightNumber":65,"airlineCode":"EY","operatingAirlineCode":"EY","stopAirports":[],"departureTerminal":"3","arrivalTerminal":"C"},"origin":"AUH","destination":"SVO","departure":"2022-08-21T03:35:00","arrival":"2022-08-21T08:25:00","bookingClass":"Y","layoverDuration":0,"fareBasis":"YF1OW","subjectToGovernmentApproval":false,"fareComponentBeginAirport":"AUH","fareComponentEndAirport":"SVO","fareComponentDirectionality":"FROM","meals":[{"passengerType":"ADT","mealCode":"M"}]}],"stops":1,"totalDuration":1075,"connectionInformations":[{"@id":"33","duration":525,"changeOfAirport":false}],"bookingClass":"Y","programIDs":["124499"],"programCodes":["EYA"]}],"cabinClass":"Economy","offerInformation":{"discounted":false,"negotiated":false,"negotiatedType":"NONE"},"status":"AVAILABLE","departureDates":["2022-08-20"],"total":{"alternatives":[[{"amount":2364.61,"currency":"USD"}]]},"fare":{"alternatives":[[{"amount":2192.00,"currency":"USD"}]]},"taxes":{"alternatives":[[{"amount":172.61,"currency":"USD"}]]}},{"brandId":"YF","soldout":false,"bundlePrice":{},"availableObFees":[],"seatsRemaining":{"count":9,"lowAvailability":false},"itineraryPart":[{"@type":"ItineraryPart","@id":"34","segments":[{"@type":"Segment","@id":"35","segmentOfferInformation":{"flightsMiles":1296,"awardFare":false},"duration":200,"cabinClass":"Economy","equipment":"789","flight":{"flightNumber":599,"operatingFlightNumber":599,"airlineCode":"EY","operatingAirlineCode":"EY","stopAirports":[],"departureTerminal":"3","arrivalTerminal":"3"},"origin":"TLV","destination":"AUH","departure":"2022-08-21T15:15:00","arrival":"2022-08-21T19:35:00","bookingClass":"Y","layoverDuration":0,"fareBasis":"YF1OW","subjectToGovernmentApproval":false,"fareComponentBeginAirport":"TLV","fareComponentEndAirport":"AUH","fareComponentDirectionality":"FROM","meals":[{"passengerType":"ADT","mealCode":"M"}]},{"@type":"Segment","@id":"36","segmentOfferInformation":{"flightsMiles":2339,"awardFare":false},"duration":350,"cabinClass":"Economy","equipment":"781","flight":{"flightNumber":65,"operatingFlightNumber":65,"airlineCode":"EY","operatingAirlineCode":"EY","stopAirports":[],"departureTerminal":"3","arrivalTerminal":"C"},"origin":"AUH","destination":"SVO","departure":"2022-08-22T03:35:00","arrival":"2022-08-22T08:25:00","bookingClass":"Y","layoverDuration":0,"fareBasis":"YF1OW","subjectToGovernmentApproval":false,"fareComponentBeginAirport":"AUH","fareComponentEndAirport":"SVO","fareComponentDirectionality":"FROM","meals":[{"passengerType":"ADT","mealCode":"M"}]}],"stops":1,"totalDuration":1030,"connectionInformations":[{"@id":"37","duration":480,"changeOfAirport":false}],"bookingClass":"Y","programIDs":["124499"],"programCodes":["EYA"]}],"cabinClass":"Economy","offerInformation":{"discounted":false,"negotiated":false,"negotiatedType":"NONE"},"status":"AVAILABLE","departureDates":["2022-08-21"],"total":{"alternatives":[[{"amount":2364.61,"currency":"USD"}]]},"fare":{"alternatives":[[{"amount":2192.00,"currency":"USD"}]]},"taxes":{"alternatives":[[{"amount":172.61,"currency":"USD"}]]}},{"brandId":"YF","soldout":false,"bundlePrice":{},"availableObFees":[],"seatsRemaining":{"count":9,"lowAvailability":false},"itineraryPart":[{"@type":"ItineraryPart","@id":"38","segments":[{"@type":"Segment","@id":"39","segmentOfferInformation":{"flightsMiles":1296,"awardFare":false},"duration":200,"cabinClass":"Economy","equipment":"321","flight":{"flightNumber":599,"operatingFlightNumber":599,"airlineCode":"EY","operatingAirlineCode":"EY","stopAirports":[],"departureTerminal":"3","arrivalTerminal":"3"},"origin":"TLV","destination":"AUH","departure":"2022-08-22T14:30:00","arrival":"2022-08-22T18:50:00","bookingClass":"Y","layoverDuration":0,"fareBasis":"YF1OW","subjectToGovernmentApproval":false,"fareComponentBeginAirport":"TLV","fareComponentEndAirport":"AUH","fareComponentDirectionality":"FROM","meals":[{"passengerType":"ADT","mealCode":"M"}]},{"@type":"Segment","@id":"40","segmentOfferInformation":{"flightsMiles":2339,"awardFare":false},"duration":350,"cabinClass":"Economy","equipment":"781","flight":{"flightNumber":65,"operatingFlightNumber":65,"airlineCode":"EY","operatingAirlineCode":"EY","stopAirports":[],"departureTerminal":"3","arrivalTerminal":"C"},"origin":"AUH","destination":"SVO","departure":"2022-08-23T03:35:00","arrival":"2022-08-23T08:25:00","bookingClass":"Y","layoverDuration":0,"fareBasis":"YF1OW","subjectToGovernmentApproval":false,"fareComponentBeginAirport":"AUH","fareComponentEndAirport":"SVO","fareComponentDirectionality":"FROM","meals":[{"passengerType":"ADT","mealCode":"M"}]}],"stops":1,"totalDuration":1075,"connectionInformations":[{"@id":"41","duration":525,"changeOfAirport":false}],"bookingClass":"Y","programIDs":["124499"],"programCodes":["EYA"]}],"cabinClass":"Economy","offerInformation":{"discounted":false,"negotiated":false,"negotiatedType":"NONE"},"status":"AVAILABLE","departureDates":["2022-08-22"],"total":{"alternatives":[[{"amount":2364.61,"currency":"USD"}]]},"fare":{"alternatives":[[{"amount":2192.00,"currency":"USD"}]]},"taxes":{"alternatives":[[{"amount":172.61,"currency":"USD"}]]}}]],"bundledOffers":[],"bundledAlternateDateOffers":[],"brandedResults":{"itineraryPartBrands":[[{"itineraryPart":{"@ref":"1"},"brandOffers":[{"shoppingBasketHashCode":-737958418,"brandId":"YF","soldout":false,"bundlePrice":{},"availableObFees":[],"seatsRemaining":{"count":9,"lowAvailability":false},"cabinClass":"Economy","offerInformation":{"discounted":false,"negotiated":false,"negotiatedType":"NONE"},"advisories":[],"total":{"alternatives":[[{"amount":2364.61,"currency":"USD"}]]},"fare":{"alternatives":[[{"amount":2192.00,"currency":"USD"}]]},"totalMandatoryObFees":{"alternatives":[]},"taxes":{"alternatives":[[{"amount":172.61,"currency":"USD"}]]}},{"shoppingBasketHashCode":1522231966,"brandId":"JF","soldout":false,"bundlePrice":{},"availableObFees":[],"seatsRemaining":{"count":3,"lowAvailability":false},"cabinClass":"Business","offerInformation":{"discounted":false,"negotiated":false,"negotiatedType":"NONE"},"advisories":[],"total":{"alternatives":[[{"amount":9670.61,"currency":"USD"}]]},"fare":{"alternatives":[[{"amount":9258.00,"currency":"USD"}]]},"totalMandatoryObFees":{"alternatives":[]},"taxes":{"alternatives":[[{"amount":412.61,"currency":"USD"}]]}}],"duration":1075,"departure":"2022-08-19T14:30:00","arrival":"2022-08-20T08:25:00"},{"itineraryPart":{"@ref":"9"},"brandOffers":[{"shoppingBasketHashCode":1186964908,"brandId":"YF","soldout":false,"bundlePrice":{},"availableObFees":[],"seatsRemaining":{"count":4,"lowAvailability":false},"cabinClass":"Economy","offerInformation":{"discounted":false,"negotiated":false,"negotiatedType":"NONE"},"advisories":[],"total":{"alternatives":[[{"amount":2553.29,"currency":"USD"}]]},"fare":{"alternatives":[[{"amount":2284.00,"currency":"USD"}]]},"totalMandatoryObFees":{"alternatives":[]},"taxes":{"alternatives":[[{"amount":269.29,"currency":"USD"}]]}}],"duration":1210,"departure":"2022-08-19T12:15:00","arrival":"2022-08-20T08:25:00"}]]},"travelPartAdvisories":[[]],"soldOutDatesOutbound":[],"soldOutDatesInbound":[],"noneScheduledDatesOutbound":[],"noneScheduledDatesInbound":[],"warnings":[],"currency":"USD","promocodeValid":false,"negotiateFarePresent":false,"conversionRatesFound":false}